django_logger_panel/__init__.py
django_logger_panel/__version__.py
django_logger_panel/apps.py
django_logger_panel/core.py
django_logger_panel/exceptions.py
django_logger_panel/serializers.py
django_logger_panel/tests.py
django_logger_panel/urls.py
django_logger_panel/static/loggerpanel/css/default.css
django_logger_panel/templates/loggerpanel/base.html
django_logger_panel/templates/loggerpanel/detail.html
django_logger_panel/templates/loggerpanel/loggers.html
django_logger_panel/templatetags/__init__.py
django_logger_panel/templatetags/loggerpanel.py
django_logger_panel/views/__init__.py
django_logger_panel/views/base.py
django_logger_panel/views/logger.py
tests/__init__.py
tests/conftest.py
tests/test_serializers.py
tests/test_url.py
tests/urls.py
django_logger_panel-0.1.6.dist-info/LICENSE
django_logger_panel-0.1.6.dist-info/METADATA
django_logger_panel-0.1.6.dist-info/WHEEL
django_logger_panel-0.1.6.dist-info/top_level.txt
django_logger_panel-0.1.6.dist-info/RECORD
