Metadata-Version: 2.1
Name: django-logger-panel
Version: 0.1.6
Summary: An easy way to change the log level in runtime.
Home-page: https://github.com/jonathadv/django-logger-panel
Author: Jonatha Daguerre
Author-email: jonatha@daguerre.com.br
License: MIT
Platform: UNKNOWN
Classifier: Development Status :: 4 - Beta
Classifier: Intended Audience :: Developers
Classifier: Natural Language :: English
Classifier: License :: OSI Approved :: MIT License
Classifier: Programming Language :: Python
Classifier: Programming Language :: Python :: 3.6
Classifier: Programming Language :: Python :: 3.7
Classifier: Programming Language :: Python :: 3.8
Classifier: Programming Language :: Python :: 3.9
Classifier: Programming Language :: Python :: 3 :: Only
Classifier: Programming Language :: Python :: Implementation :: CPython
Requires-Python: >=3.6.0
Requires-Dist: django
